{
  "version": 2,
  "extractor": "pdffigures2",
  "figures": [
    {
      "url": "assets/figures/arxiv/2604.12147v1/fig-001.webp",
      "caption": "Figure 6: Phase flow analysis under No Reproduction (L★(Φ) = N P V ) and No Validation plan setting (L★(Φ) = N R P ).",
      "page": 7,
      "index": 1,
      "width": 1053,
      "height": 284
    },
    {
      "url": "assets/figures/arxiv/2604.12147v1/fig-002.webp",
      "caption": "Figure 7: Impact of No Reproduction plan (a) and No Validation plan (b) on the success rate.",
      "page": 7,
      "index": 2,
      "width": 1056,
      "height": 233
    },
    {
      "url": "assets/figures/arxiv/2604.12147v1/fig-003.webp",
      "caption": "Figure 19: Compliance metrics on SWE-bench Verified deter-",
      "page": 10,
      "index": 3,
      "width": 454,
      "height": 279
    },
    {
      "url": "assets/figures/arxiv/2604.12147v1/fig-004.webp",
      "caption": "Figure 1: Illustrative examples of agent trajectories and their corresponding Graphectory and Langutory representations.",
      "page": 3,
      "index": 4,
      "width": 970,
      "height": 354
    },
    {
      "url": "assets/figures/arxiv/2604.12147v1/fig-005.webp",
      "caption": "Figure 10: Phase flow analysis under Regression Testing (L★(Φ) = 𝑅𝐺 N R P V 𝑉𝐺 ) and Summary plan setting (L★(Φ) =",
      "page": 8,
      "index": 5,
      "width": 1044,
      "height": 275
    },
    {
      "url": "assets/figures/arxiv/2604.12147v1/fig-006.webp",
      "caption": "Table 1: Summary of studied plan settings, their corresponding formulation, and type of plan variation.",
      "page": 4,
      "index": 6,
      "width": 1006,
      "height": 203
    },
    {
      "url": "assets/figures/arxiv/2604.12147v1/fig-007.webp",
      "caption": "Figure 2: Standard plan compliance metrics and success rate for studied trajectories across all models.",
      "page": 4,
      "index": 7,
      "width": 1036,
      "height": 229
    },
    {
      "url": "assets/figures/arxiv/2604.12147v1/fig-008.webp",
      "caption": "Figure 14: Phase flow analysis under Reordered (L★(Φ) = N P R V ) and Reminded setting (L★(Φ) = N R P V ).",
      "page": 9,
      "index": 8,
      "width": 1044,
      "height": 239
    },
    {
      "url": "assets/figures/arxiv/2604.12147v1/fig-009.webp",
      "caption": "Figure 3: Phase flow analysis under Standard plan (L★(Φ) = N R P V ). Flow thickness notes the proportion of trajectories",
      "page": 5,
      "index": 9,
      "width": 1059,
      "height": 484
    }
  ]
}